_zivid/__init__.py
_zivid/_zividcore.cp37-win_amd64.pyd
_zivid/_zividvisualization.pyd
zivid/__init__.py
zivid/_local_point_cloud_registration_parameters.py
zivid/_suggest_settings_parameters.py
zivid/_version.py
zivid/application.py
zivid/calibration.py
zivid/camera.py
zivid/camera_info.py
zivid/camera_intrinsics.py
zivid/camera_state.py
zivid/capture_assistant.py
zivid/firmware.py
zivid/frame.py
zivid/frame_2d.py
zivid/frame_info.py
zivid/image.py
zivid/matrix4x4.py
zivid/network_configuration.py
zivid/point_cloud.py
zivid/presets.py
zivid/projection.py
zivid/scene_conditions.py
zivid/sdk_version.py
zivid/settings.py
zivid/settings2d.py
zivid/unorganized_point_cloud.py
zivid/visualization.py
zivid/_calibration/__init__.py
zivid/_calibration/detector.py
zivid/_calibration/hand_eye.py
zivid/_calibration/infield_correction.py
zivid/_calibration/multi_camera.py
zivid/_calibration/pose.py
zivid/experimental/__init__.py
zivid/experimental/_pixel_mapping.py
zivid/experimental/calibration.py
zivid/experimental/hand_eye_low_dof.py
zivid/experimental/point_cloud_export/__init__.py
zivid/experimental/point_cloud_export/_export_frame.py
zivid/experimental/point_cloud_export/_export_unorganized_point_cloud.py
zivid/experimental/point_cloud_export/file_format.py
zivid/experimental/toolbox/__init__.py
zivid/experimental/toolbox/barcode.py
zivid/experimental/toolbox/point_cloud_registration.py
zivid-2.17.2.dist-info/LICENSE
zivid-2.17.2.dist-info/METADATA
zivid-2.17.2.dist-info/WHEEL
zivid-2.17.2.dist-info/top_level.txt
zivid-2.17.2.dist-info/RECORD
