Metadata-Version: 2.4
Name: zivid
Version: 2.17.2
Summary: Defining the Future of 3D Machine Vision
Home-page: https://www.zivid.com
Author: Zivid AS
Author-email: customersuccess@zivid.com
License: BSD 3-Clause
Classifier: License :: OSI Approved :: BSD License
Classifier: Programming Language :: Python :: 3
Classifier: Programming Language :: Python :: Implementation :: CPython
Classifier: Topic :: Scientific/Engineering
License-File: LICENSE
Requires-Dist: numpy
Dynamic: author
Dynamic: author-email
Dynamic: classifier
Dynamic: description
Dynamic: description-content-type
Dynamic: home-page
Dynamic: license
Dynamic: license-file
Dynamic: requires-dist
Dynamic: summary
